{
  "type": "FeatureCollection",
  "generator": "GraphDefined OSM Importer",
  "copyright": "The data included in this document is from www.openstreetmap.org. The data is made available under ODbL.",
  "timestamp": "2014-12-16T10:42:05.551Z",
  "features": [
    {
      "type": "Feature",
      "id": "node/2601037424",
      "properties": {
        "@id": "node/2601037424",
        "addr:city": "Jena",
        "addr:country": "DE",
        "addr:housenumber": "15",
        "addr:postcode": "07745",
        "addr:street": "Alte Hauptstraße",
        "addr:suburb": "Göschwitz",
        "amenity": "college",
        "contact:website": "http://www.waldorf-fernstudium.de/",
        "name": "Fernstudium WaldorfPädagogik",
        "operator": "Fernstudium WaldorfPädagogik & Coaching e.V."
      },
      "geometry": {
        "type": "Point",
        "coordinates": [
          11.5899208,
          50.8785745
        ]
      }
    }
  ]
}